README.txt
setup.py
src/mekk/__init__.py
src/mekk.calibre.egg-info/PKG-INFO
src/mekk.calibre.egg-info/SOURCES.txt
src/mekk.calibre.egg-info/dependency_links.txt
src/mekk.calibre.egg-info/entry_points.txt
src/mekk.calibre.egg-info/namespace_packages.txt
src/mekk.calibre.egg-info/requires.txt
src/mekk.calibre.egg-info/top_level.txt
src/mekk.calibre.egg-info/zip-safe
src/mekk/calibre/__init__.py
src/mekk/calibre/calibre_util.py
src/mekk/calibre/config.py
src/mekk/calibre/disk_util.py
src/mekk/calibre/isbn.py
src/mekk/calibre/openoffice.py
src/mekk/calibre/sony_prs.py
src/mekk/calibre/text_extract.py
src/mekk/calibre/version.py
src/mekk/calibre/scripts/__init__.py
src/mekk/calibre/scripts/add_if_missing.py
src/mekk/calibre/scripts/convert_docs_to_rtf.py
src/mekk/calibre/scripts/find_books_missing_in_database.py
src/mekk/calibre/scripts/guess_and_add_isbn.py
src/mekk/calibre/scripts/report_duplicates.py