Metadata-Version: 1.1
Name: mekk.calibre
Version: 1.3.1
Summary: Calibre helper scripts (ISBN guessing, RTF to DOC conversion,hanging books detection, ...).
Home-page: http://mekk.waw.pl/
Author: Marcin Kasperski
Author-email: Marcin.Kasperski@mekk.waw.pl
License: BSD
Keywords: org
Platform: UNKNOWN
Classifier: Programming Language :: Python :: 2
Classifier: Programming Language :: Python :: 3
Classifier: Intended Audience :: End Users/Desktop
Classifier: Topic :: Utilities
Classifier: Development Status :: 4 - Beta
Classifier: Environment :: Console
Classifier: Programming Language :: Python :: 2
